[{
	"_id": {
		"$oid": "5a9920d056e76a31dcbd4d68"
	},
	"name": "laptop",
	"price": 2000,
	"component": "c5",
	"seller": "lozi",
	"createdAt": {
		"$date": "2018-03-02T10:00:48.756Z"
	},
	"__v": 0
},
{
	"_id": {
		"$oid": "5a9920dc56e76a31dcbd4d69"
	},
	"name": "mobile",
	"price": 1000,
	"component": "c5",
	"seller": "lozi",
	"createdAt": {
		"$date": "2018-03-02T10:01:00.092Z"
	},
	"__v": 0
},
{
	"_id": {
		"$oid": "5a99211256e76a31dcbd4d6b"
	},
	"name": "fifa 18",
	"price": 150,
	"component": "c5",
	"seller": "lozi",
	"createdAt": {
		"$date": "2018-03-02T10:01:54.194Z"
	},
	"__v": 0
},
{
	"_id": {
		"$oid": "5a9923a656e76a31dcbd4d6c"
	},
	"name": "watch",
	"price": 700,
	"component": "c5",
	"seller": "lozi",
	"createdAt": {
		"$date": "2018-03-02T10:12:54.968Z"
	},
	"__v": 0
},
{
	"_id": {
		"$oid": "5a9920eb56e76a31dcbd4d6a"
	},
	"name": "headphones",
	"price": 300,
	"component": "c5",
	"seller": "lozi",
	"createdAt": {
		"$date": "2018-03-02T10:01:15.716Z"
	},
	"__v": 0
},
{
	"_id": {
		"$oid": "5a996d576d613441246b2bff"
	},
	"name": "laptop",
	"price": 1000,
	"component": "c2",
	"seller": "lozy",
	"createdAt": {
		"$date": "2018-03-02T15:27:19.392Z"
	},
	"__v": 0
},
{
	"_id": {
		"$oid": "5a996d856d613441246b2c00"
	},
	"name": "mobile",
	"price": 500,
	"component": "c5",
	"seller": "lozy",
	"createdAt": {
		"$date": "2018-03-02T15:28:05.460Z"
	},
	"__v": 0
},
{
	"_id": {
		"$oid": "5a9857034a7f482304455be6"
	},
	"name": "external hard disk",
	"price": 700,
	"component": "c5",
	"seller": "lozi",
	"createdAt": {
		"$date": "2018-03-01T19:39:47.357Z"
	},
	"__v": 0,
	"updatedAt": {
		"$date": "2018-03-02T10:17:02.619Z"
	}
},
{
	"_id": {
		"$oid": "5a993a8685e20b3e7c5d3a03"
	},
	"name": "reading light",
	"price": 300,
	"component": "c5",
	"seller": "nadine",
	"createdAt": {
		"$date": "2018-03-02T11:50:30.356Z"
	},
	"__v": 0
},
{
	"_id": {
		"$oid": "5a993a6685e20b3e7c5d3a02"
	},
	"name": "iphone",
	"price": 15000,
	"component": "c5",
	"seller": "nadine",
	"createdAt": {
		"$date": "2018-03-02T11:49:58.505Z"
	},
	"__v": 0
},
{
	"_id": {
		"$oid": "5a993a9f85e20b3e7c5d3a04"
	},
	"name": "ultraviolet lamp",
	"price": 500,
	"component": "c5",
	"seller": "nadine",
	"createdAt": {
		"$date": "2018-03-02T11:50:55.672Z"
	},
	"__v": 0
},
{
	"_id": {
		"$oid": "5a993ab885e20b3e7c5d3a05"
	},
	"name": "digital dictionary scanner",
	"price": 100,
	"component": "c5",
	"seller": "nadine",
	"createdAt": {
		"$date": "2018-03-02T11:51:20.510Z"
	},
	"__v": 0
},
{
	"_id": {
		"$oid": "5a993ac685e20b3e7c5d3a06"
	},
	"name": "laptop xii",
	"price": 7050,
	"component": "c5",
	"seller": "nadine",
	"createdAt": {
		"$date": "2018-03-02T11:51:34.721Z"
	},
	"__v": 0,
	"updatedAt": {
		"$date": "2018-03-02T17:56:51.926Z"
	}
},
{
	"_id": {
		"$oid": "5a99bdb1a7edac0f40aad8ae"
	},
	"name": "omarr",
	"price": 1232,
	"component": "c5",
	"seller": "omar elsobky",
	"createdAt": {
		"$date": "2018-03-02T21:10:09.033Z"
	},
	"__v": 0
},
{
	"_id": {
		"$oid": "5a9954c10e657634ec223c99"
	},
	"name": "omar",
	"price": 5000,
	"component": "c5",
	"seller": "omar elsobky",
	"createdAt": {
		"$date": "2018-03-02T13:42:25.841Z"
	},
	"__v": 0,
	"updatedAt": {
		"$date": "2018-03-02T13:42:45.303Z"
	}
},
{
	"_id": {
		"$oid": "5a99bdc1a7edac0f40aad8af"
	},
	"name": "tv3",
	"price": 1233333,
	"component": "c5",
	"seller": "omar elsobky",
	"createdAt": {
		"$date": "2018-03-02T21:10:25.799Z"
	},
	"__v": 0
},
{
	"_id": {
		"$oid": "5a99bd91a7edac0f40aad8ac"
	},
	"name": "tv",
	"price": 331212,
	"component": "c5",
	"seller": "omar elsobky",
	"createdAt": {
		"$date": "2018-03-02T21:09:37.809Z"
	},
	"__v": 0
},
{
	"_id": {
		"$oid": "5a99bda2a7edac0f40aad8ad"
	},
	"name": "tv2",
	"price": 132123,
	"component": "c5",
	"seller": "omar elsobky",
	"createdAt": {
		"$date": "2018-03-02T21:09:54.253Z"
	},
	"__v": 0
},
{
	"_id": {
		"$oid": "5a9857e7cac510130882c738"
	},
	"name": "mobile",
	"price": 3500,
	"component": "c5",
	"seller": "pery",
	"createdAt": {
		"$date": "2018-03-01T19:43:35.658Z"
	},
	"__v": 0,
	"updatedAt": {
		"$date": "2018-03-01T20:02:40.526Z"
	}
},
{
	"_id": {
		"$oid": "5a985844cac510130882c73b"
	},
	"name": "fridge",
	"price": 12000,
	"component": "c5",
	"seller": "pery",
	"createdAt": {
		"$date": "2018-03-01T19:45:08.654Z"
	},
	"__v": 0,
	"updatedAt": {
		"$date": "2018-03-02T12:56:02.225Z"
	}
},
{
	"_id": {
		"$oid": "5a985829cac510130882c73a"
	},
	"name": "washingmachine",
	"price": 4000,
	"component": "c5",
	"seller": "pery",
	"createdAt": {
		"$date": "2018-03-01T19:44:41.837Z"
	},
	"__v": 0
},
{
	"_id": {
		"$oid": "5a9858deaa78db0db88bfd38"
	},
	"name": "laptops",
	"price": 14000,
	"component": "c5",
	"seller": "pery",
	"createdAt": {
		"$date": "2018-03-01T19:47:42.046Z"
	},
	"__v": 0
},
{
	"_id": {
		"$oid": "5a9930030519b301f87970a7"
	},
	"name": "dryer",
	"price": 1200,
	"component": "c5",
	"seller": "pery",
	"createdAt": {
		"$date": "2018-03-02T11:05:39.984Z"
	},
	"__v": 0
},
{
	"_id": {
		"$oid": "5a9948a33f1f6e21b040a610"
	},
	"name": "air conditioner",
	"price": 6090,
	"component": "c5",
	"seller": "pery",
	"createdAt": {
		"$date": "2018-03-02T12:50:43.427Z"
	},
	"__v": 0
},
{
	"_id": {
		"$oid": "5a985807cac510130882c739"
	},
	"name": "television",
	"price": 1500,
	"component": "c5",
	"seller": "lozi",
	"createdAt": {
		"$date": "2018-03-01T19:44:07.818Z"
	},
	"__v": 0,
	"updatedAt": {
		"$date": "2018-03-02T18:04:49.361Z"
	}
}]

